DEAPack/__init__.py
DEAPack/bbc.py
DEAPack/ccr.py
DEAPack/ddf.py
DEAPack/dea.py
DEAPack/model.py
DEAPack/solver.py
DEAPack/utilities.py
DEAPack/data/example_data.csv
deapack-0.1.3.dist-info/METADATA
deapack-0.1.3.dist-info/WHEEL
deapack-0.1.3.dist-info/licenses/LICENSE
deapack-0.1.3.dist-info/RECORD
